{
"type": "FeatureCollection",
"name": "start",
"crs": { "type": "name", "properties": { "name": "urn:ogc:def:crs:OGC:1.3:CRS84" } },
"features": [
{ "type": "Feature", "properties": { "id": null }, "geometry": { "type": "Point", "coordinates": [ 131.893384775116118, 43.02348103178047 ] } }
]
}
